skmisc/_version.py
skmisc/__init__.py
skmisc/_distributor_init.py
skmisc/__config__.py
skmisc/loess/__init__.py
skmisc/loess/_loess.cpython-312-darwin.so
skmisc/loess/tests/co2_data
skmisc/loess/tests/madeup_data
skmisc/loess/tests/co2_results_double
skmisc/loess/tests/madeup_result
skmisc/loess/tests/test_loess.py
skmisc/loess/tests/__init__.py
skmisc/loess/tests/gas_data
skmisc/loess/tests/gas_result
skmisc/loess/tests/co2_results_real
scikit_misc-0.5.2.dist-info/RECORD
scikit_misc-0.5.2.dist-info/LICENSE
scikit_misc-0.5.2.dist-info/WHEEL
scikit_misc-0.5.2.dist-info/METADATA
