Metadata-Version: 2.1
Name: scikit-misc
Version: 0.5.2
Summary: Miscellaneous tools for scientific computing.
Author-Email: Hassan Kibirige <has2k1@gmail.com>
License: Copyright (c) 2016, Hassan Kibirige
Classifier: Intended Audience :: Science/Research
Classifier: License :: OSI Approved :: BSD License
Classifier: Operating System :: Unix
Classifier: Operating System :: MacOS
Classifier: Operating System :: Microsoft :: Windows
Classifier: Operating System :: POSIX
Classifier: Programming Language :: C
Classifier: Programming Language :: Fortran
Classifier: Programming Language :: Python :: 3
Classifier: Programming Language :: Python :: 3.10
Classifier: Programming Language :: Python :: 3.11
Classifier: Programming Language :: Python :: 3.12
Classifier: Programming Language :: Python :: 3.13
Classifier: Programming Language :: Python :: 3.14
Classifier: Topic :: Scientific/Engineering
Project-URL: homepage, https://has2k1.github.io/scikit-misc/stable
Project-URL: repository, https://github.com/has2k1/scikit-misc
Project-URL: documentation, https://has2k1.github.io/scikit-misc/stable
Project-URL: changelog, https://has2k1.github.io/scikit-misc/stable/changelog.html
Requires-Python: >=3.10
Requires-Dist: numpy>=1.26.4
Provides-Extra: all
Requires-Dist: scikit-misc[doc]; extra == "all"
Requires-Dist: scikit-misc[build]; extra == "all"
Requires-Dist: scikit-misc[lint]; extra == "all"
Requires-Dist: scikit-misc[test]; extra == "all"
Requires-Dist: scikit-misc[dev]; extra == "all"
Provides-Extra: doc
Requires-Dist: numpydoc; extra == "doc"
Requires-Dist: sphinx; extra == "doc"
Provides-Extra: build
Requires-Dist: cython; extra == "build"
Requires-Dist: build; extra == "build"
Requires-Dist: spin; extra == "build"
Requires-Dist: meson; extra == "build"
Requires-Dist: meson-python; extra == "build"
Requires-Dist: ninja; extra == "build"
Provides-Extra: lint
Requires-Dist: ruff; extra == "lint"
Provides-Extra: test
Requires-Dist: pytest-cov; extra == "test"
Provides-Extra: dev
Requires-Dist: wheel; extra == "dev"
Requires-Dist: twine; extra == "dev"
